meteodatalab/__init__.py
meteodatalab/cli.py
meteodatalab/config.py
meteodatalab/data/fdb_config_balfrin.yaml
meteodatalab/data/fdb_config_tsa.yaml
meteodatalab/data/field_mappings.yml
meteodatalab/data_cache.py
meteodatalab/data_source.py
meteodatalab/grib_decoder.py
meteodatalab/icon_grid.py
meteodatalab/mars.py
meteodatalab/mch_model_data.py
meteodatalab/metadata.py
meteodatalab/ogd_api.py
meteodatalab/operators/__init__.py
meteodatalab/operators/atmo.py
meteodatalab/operators/brn.py
meteodatalab/operators/clip.py
meteodatalab/operators/crop.py
meteodatalab/operators/curl.py
meteodatalab/operators/destagger.py
meteodatalab/operators/diff.py
meteodatalab/operators/flexpart.py
meteodatalab/operators/gis.py
meteodatalab/operators/hzerocl.py
meteodatalab/operators/internal/theta.py
meteodatalab/operators/lateral_operators.py
meteodatalab/operators/omega_slope.py
meteodatalab/operators/pot_vortic.py
meteodatalab/operators/radiation.py
meteodatalab/operators/regrid.py
meteodatalab/operators/relhum.py
meteodatalab/operators/rho.py
meteodatalab/operators/support_operators.py
meteodatalab/operators/theta.py
meteodatalab/operators/thetav.py
meteodatalab/operators/time_operators.py
meteodatalab/operators/total_diff.py
meteodatalab/operators/vertical_extrapolation.py
meteodatalab/operators/vertical_interpolation.py
meteodatalab/operators/vertical_reduction.py
meteodatalab/operators/wind.py
meteodatalab/physical_constants.py
meteodatalab/product.py
meteodatalab/products/ninjo_k2th.py
meteodatalab/py.typed
meteodatalab/tasking.py
meteodatalab/util.py
meteodata_lab-0.5.0.dist-info/LICENSE
meteodata_lab-0.5.0.dist-info/METADATA
meteodata_lab-0.5.0.dist-info/WHEEL
meteodata_lab-0.5.0.dist-info/entry_points.txt
meteodata_lab-0.5.0.dist-info/RECORD
