Metadata-Version: 2.3
Name: meteodata-lab
Version: 0.5.0
Summary: A data post-processing framework on the basis of xarray.
Keywords: Icon,Data Processing
Author: Carlos Osuna
Author-email: carlos.osuna@meteoswiss.ch
Requires-Python: >=3.10,<3.13
Classifier: Development Status :: 2 - Pre-Alpha
Classifier: Intended Audience :: Developers
Classifier: Natural Language :: English
Classifier: Programming Language :: Python :: 3
Classifier: Programming Language :: Python :: 3.10
Classifier: Programming Language :: Python :: 3.11
Classifier: Programming Language :: Python :: 3.12
Provides-Extra: polytope
Provides-Extra: regrid
Requires-Dist: click (>=8.1.7,<9.0.0)
Requires-Dist: earthkit-data[covjsonkit] (>=0.11,<1)
Requires-Dist: earthkit-meteo (>=0.4.0)
Requires-Dist: eccodes (>=2.38,<2.40)
Requires-Dist: eccodes-cosmo-resources-python (>=2.38,<2.39)
Requires-Dist: numpy (>=1.26.4,<2.4.0)
Requires-Dist: polytope-client (>=0.7.4,<0.8.0) ; extra == "polytope"
Requires-Dist: pydantic
Requires-Dist: pyproj (>=3.6.1,<4.0.0) ; extra == "regrid"
Requires-Dist: pyyaml (>=6.0.1,<7.0.0)
Requires-Dist: rasterio (>=1.3.10,<2.0.0) ; extra == "regrid"
Requires-Dist: scipy (>=1.13,<2.0) ; extra == "regrid"
Requires-Dist: setuptools
Requires-Dist: xarray (>=2024)
Project-URL: documentation, https://meteoswiss.github.io/meteodata-lab/
Project-URL: source, https://github.com/MeteoSwiss/meteodata-lab
